llmverse/__init__.py
llmverse/data_prep.py
llmverse/download.py
llmverse/finetune.py
llmverse/inference.py
llmverse/load_finetuned_llm.py
llmverse-0.1.3.dist-info/LICENSE
llmverse-0.1.3.dist-info/METADATA
llmverse-0.1.3.dist-info/WHEEL
llmverse-0.1.3.dist-info/top_level.txt
llmverse-0.1.3.dist-info/RECORD
