Metadata-Version: 2.1
Name: llmverse
Version: 0.1.3
Summary: LLM-Universe: One-Stop Solution for All Open-Source LLMs, from Downloading and Quantizing to Generating Responses and Fine-Tuning.
Author-email: Nilavo Boral <nilavoboral@gmail.com>
Classifier: Programming Language :: Python :: 3
Classifier: License :: OSI Approved :: MIT License
Classifier: Operating System :: OS Independent
Requires-Python: >=3.8
License-File: LICENSE
Requires-Dist: packaging
Requires-Dist: wheel
Requires-Dist: pandas
Requires-Dist: matplotlib
Requires-Dist: torch
Requires-Dist: transformers
Requires-Dist: peft
Requires-Dist: datasets
Requires-Dist: bitsandbytes
Requires-Dist: accelerate
Requires-Dist: flash-attn
Requires-Dist: sentencepiece
Requires-Dist: wandb
